pyvidfetcher/__init__.py
pyvidfetcher/__main__.py
pyvidfetcher-1.1.1.dist-info/METADATA
pyvidfetcher-1.1.1.dist-info/WHEEL
pyvidfetcher-1.1.1.dist-info/entry_points.txt
pyvidfetcher-1.1.1.dist-info/top_level.txt
pyvidfetcher-1.1.1.dist-info/RECORD
